sigma_pi/__init__.py
sigma_pi-0.3.0.dist-info/METADATA
sigma_pi-0.3.0.dist-info/WHEEL
sigma_pi-0.3.0.dist-info/licenses/LICENSE
sigma_pi-0.3.0.dist-info/RECORD
