Metadata-Version: 2.4
Name: sigma-pi
Version: 0.3.0
Summary: A lightweight tool to calculate Predictive Integrity (PI) for PyTorch models.
Project-URL: Homepage, https://github.com/dmf-archive/SigmaPI
Project-URL: Bug Tracker, https://github.com/dmf-archive/SigmaPI/issues
Author-email: dmf-archive <Lin.Rui.ipwt@proton.me>
License: MIT License
License-File: LICENSE
Classifier: Development Status :: 3 - Alpha
Classifier: Intended Audience :: Developers
Classifier: Intended Audience :: Science/Research
Classifier: License :: OSI Approved :: MIT License
Classifier: Operating System :: OS Independent
Classifier: Programming Language :: Python :: 3
Classifier: Programming Language :: Python :: 3.8
Classifier: Programming Language :: Python :: 3.9
Classifier: Programming Language :: Python :: 3.10
Classifier: Programming Language :: Python :: 3.11
Classifier: Programming Language :: Python :: 3.12
Classifier: Topic :: Scientific/Engineering :: Artificial Intelligence
Classifier: Topic :: Software Development :: Libraries :: Python Modules
Requires-Python: >=3.8
Provides-Extra: dev
Requires-Dist: build; extra == 'dev'
Requires-Dist: hatch; extra == 'dev'
Requires-Dist: mypy; extra == 'dev'
Requires-Dist: twine; extra == 'dev'
Provides-Extra: torch
Requires-Dist: torch; extra == 'torch'
